CHANGES.rst
CONTRIBUTORS.rst
MANIFEST.in
README.rst
setup.cfg
setup.py
docs/source/conf.py
docs/source/index.rst
docs/source/_static/logo.png
docs/source/_templates/empty
src/ps/__init__.py
src/ps.zope.i18nfield.egg-info/PKG-INFO
src/ps.zope.i18nfield.egg-info/SOURCES.txt
src/ps.zope.i18nfield.egg-info/dependency_links.txt
src/ps.zope.i18nfield.egg-info/entry_points.txt
src/ps.zope.i18nfield.egg-info/namespace_packages.txt
src/ps.zope.i18nfield.egg-info/not-zip-safe
src/ps.zope.i18nfield.egg-info/requires.txt
src/ps.zope.i18nfield.egg-info/top_level.txt
src/ps/zope/__init__.py
src/ps/zope/i18nfield/__init__.py
src/ps/zope/i18nfield/configure.zcml
src/ps/zope/i18nfield/field.py
src/ps/zope/i18nfield/fieldproperty.py
src/ps/zope/i18nfield/i18n.py
src/ps/zope/i18nfield/index.py
src/ps/zope/i18nfield/interfaces.py
src/ps/zope/i18nfield/storage.py
src/ps/zope/i18nfield/utils.py
src/ps/zope/i18nfield/locales/manual.pot
src/ps/zope/i18nfield/locales/ps.zope.i18nfield.pot
src/ps/zope/i18nfield/locales/ar/LC_MESSAGES/ps.zope.i18nfield.po
src/ps/zope/i18nfield/locales/cmn/LC_MESSAGES/ps.zope.i18nfield.po
src/ps/zope/i18nfield/locales/de/LC_MESSAGES/ps.zope.i18nfield.po
src/ps/zope/i18nfield/locales/en/LC_MESSAGES/ps.zope.i18nfield.po
src/ps/zope/i18nfield/locales/es/LC_MESSAGES/ps.zope.i18nfield.po
src/ps/zope/i18nfield/locales/et/LC_MESSAGES/ps.zope.i18nfield.po
src/ps/zope/i18nfield/locales/fr/LC_MESSAGES/ps.zope.i18nfield.po
src/ps/zope/i18nfield/locales/it/LC_MESSAGES/ps.zope.i18nfield.po
src/ps/zope/i18nfield/locales/ja/LC_MESSAGES/ps.zope.i18nfield.po
src/ps/zope/i18nfield/locales/pt/LC_MESSAGES/ps.zope.i18nfield.po
src/ps/zope/i18nfield/locales/ru/LC_MESSAGES/ps.zope.i18nfield.po
src/ps/zope/i18nfield/locales/vi/LC_MESSAGES/ps.zope.i18nfield.po
src/ps/zope/i18nfield/locales/vi_VN/LC_MESSAGES/ps.zope.i18nfield.po
src/ps/zope/i18nfield/locales/zh/LC_MESSAGES/ps.zope.i18nfield.po
src/ps/zope/i18nfield/locales/zh_TW/LC_MESSAGES/ps.zope.i18nfield.po
src/ps/zope/i18nfield/plone/__init__.py
src/ps/zope/i18nfield/plone/configure.zcml
src/ps/zope/i18nfield/plone/plone5_display.pt
src/ps/zope/i18nfield/plone/plone5_input.pt
src/ps/zope/i18nfield/plone/utils.py
src/ps/zope/i18nfield/ploneregistry/__init__.py
src/ps/zope/i18nfield/ploneregistry/adapter.py
src/ps/zope/i18nfield/ploneregistry/configure.zcml
