Metadata-Version: 1.1
Name: ps.zope.i18nfield
Version: 0.7
Summary: A zope.schema field for inline translations.
Home-page: https://github.com/propertyshelf/ps.zope.i18nfield
Author: Propertyshelf, Inc.
Author-email: development@propertyshelf.com
License: GPL
Download-URL: http://pypi.python.org/pypi/ps.zope.i18nfield
Keywords: zope zope3 schema i18n z3c.form
Platform: UNKNOWN
Classifier: Development Status :: 5 - Production/Stable
Classifier: Environment :: Web Environment
Classifier: Framework :: Zope3
Classifier: Intended Audience :: Other Audience
Classifier: License :: OSI Approved :: GNU General Public License (GPL)
Classifier: Natural Language :: English
Classifier: Operating System :: OS Independent
Classifier: Programming Language :: Python
Classifier: Programming Language :: Python :: 2.6
Classifier: Programming Language :: Python :: 2.7
Classifier: Programming Language :: Zope
